[
    {
        "Name": "TIF1",
        "TimeAdd": "2016-08-05T16:23:30.286Z",
        "Quarter": "3",
        "Year": "2016",
        "Date": "Jul-04 Aug",
        "Lastest": 1,
        "Closechg": "+1.28",
        "ValueDaychg": "-30.01",
        "Highchg": "+1.92",
        "Lowchg": "+2.72",
        "Marketchg": "+1.28",
        "Turnoverchg": "-73.24",
        "PEchg": "-",
        "PBVchg": "+1.33",
        "Yieldchg": "-1.31",
        "BookValuechg": "0.00",
        "Cashchg": null,
        "TotalAssetchg": null,
        "CurrtLiabilitieschg": null,
        "TotalLiabilitieschg": null,
        "PaidupCapchg": null,
        "Equitieschg": null,
        "Saleschg": null,
        "Revenuechg": null,
        "CostOfSaleschg": null,
        "EBITchg": null,
        "IntExpenseschg": null,
        "NetProfitschg": null,
        "EPSchg": null,
        "CurrentRatiochg": null,
        "QuickRatiochg": null,
        "DERatiochg": null,
        "IntCoveragechg": null,
        "GrossProfitMarginchg": null,
        "NetProfitsMarginchg": null,
        "ReturnToAssetchg": null,
        "ReturnToEquitychg": null,
        "AccountReciveTurnoverchg": null,
        "AverageCollecPeriodchg": null,
        "FixedAssetTurnoverchg": null,
        "InventoryTurnoverchg": null,
        "AvgSalePeriodchg": null,
        "TotalAssetTurnverchg": null,
        "Close": "7.90",
        "ValueDay": "0.25",
        "High": "7.95",
        "Low": "7.55",
        "Market": "711.00",
        "TurnOver": "0.79",
        "PE": "-",
        "PBV": "0.76",
        "BookValue": "10.42",
        "Yield": "6.80",
        "Cash": null,
        "TotalAsset": null,
        "CurrtLiabilities": null,
        "TotalLiabilities": null,
        "PaidupCap": null,
        "Equities": null,
        "Sales": null,
        "Revenue": null,
        "CostOfSales": null,
        "EBIT": null,
        "IntExpenses": null,
        "NetProfits": null,
        "EPS": null,
        "CurrentRatio": null,
        "QuickRatio": null,
        "DERatio": null,
        "IntCoverage": null,
        "GrossProfitMargin": null,
        "NetProfitsMargin": null,
        "ReturnToAsset": null,
        "ReturnToEquity": null,
        "AccountReciveTurnover": null,
        "AverageCollecPeriod": null,
        "FixedAssetTurnover": null,
        "InventoryTurnover": null,
        "AvgSalePeriod": null,
        "TotalAssetTurnver": null,
        "Period": "31/03/2016",
        "AsDate": null
    },
    {
        "Name": "TIF1",
        "TimeAdd": "2016-08-05T16:23:30.286Z",
        "Quarter": "2",
        "Year": "2016",
        "Date": "Apr-Jun",
        "cashchg": null,
        "TotalAssetchg": null,
        "CurrtLiabilitieschg": null,
        "TotalLiabilitieschg": null,
        "PaidupCapchg": null,
        "Equitieschg": null,
        "Saleschg": null,
        "Revenuechg": null,
        "CostOfSaleschg": null,
        "EBITchg": null,
        "IntExpenseschg": null,
        "NetProfitschg": null,
        "EPSchg": null,
        "CurrentRatiochg": null,
        "QuickRatiochg": null,
        "DERatiochg": null,
        "IntCoveragechg": null,
        "GrossProfitMarginchg": null,
        "NetProfitsMarginchg": null,
        "ReturnToAssetchg": null,
        "ReturnToEquitychg": null,
        "AccountReciveTurnoverchg": null,
        "AverageCollecPeriodchg": null,
        "FixedAssetTurnoverchg": null,
        "InventoryTurnoverchg": null,
        "AvgSalePeriodchg": null,
        "TotalAssetTurnverchg": null,
        "cash": null,
        "TotalAsset": null,
        "CurrtLiabilities": null,
        "TotalLiabilities": null,
        "PaidupCap": null,
        "Equities": null,
        "Sales": null,
        "Revenue": null,
        "CostOfSales": null,
        "EBIT": null,
        "IntExpenses": null,
        "NetProfits": null,
        "EPS": null,
        "CurrentRatio": null,
        "QuickRatio": null,
        "DERatio": null,
        "IntCoverage": null,
        "GrossProfitMargin": null,
        "NetProfitsMargin": null,
        "ReturnToAsset": null,
        "ReturnToEquity": null,
        "AccountReciveTurnover": null,
        "AverageCollecPeriod": null,
        "FixedAssetTurnover": null,
        "InventoryTurnover": null,
        "AvgSalePeriod": null,
        "TotalAssetTurnver": null,
        "Closechg": "+5.41",
        "ValueDaychg": "+84.84",
        "Highchg": "+4.70",
        "Lowchg": "+3.52",
        "Marketchg": "+5.41",
        "Turnoverchg": "+58.07",
        "PEchg": "-",
        "PBVchg": "+5.63",
        "Yieldchg": "-4.70",
        "BookValuechg": "-0.19",
        "Cashchg": "",
        "Close": "7.80",
        "ValueDay": "0.35",
        "High": "7.80",
        "Low": "7.35",
        "Market": "702.00",
        "TurnOver": "2.94",
        "PE": "-",
        "PBV": "0.75",
        "BookValue": "10.42",
        "Yield": "6.89",
        "AsDate": null,
        "Period": "31/03/2016"
    },
    {
        "Name": "TIF1",
        "TimeAdd": "2016-08-05T16:23:30.286Z",
        "Quarter": "1",
        "Year": "2016",
        "Date": "Jan-Mar",
        "Closechg": "+1.37",
        "ValueDaychg": "+20.62",
        "Highchg": "-1.32",
        "Lowchg": "-0.70",
        "Marketchg": "+1.37",
        "Turnoverchg": "+23.22",
        "PEchg": "-",
        "PBVchg": "0.00",
        "Yieldchg": "-1.36",
        "BookValuechg": "+2.05",
        "CurrtLiabilitieschg": ".",
        "EPSchg": "",
        "Close": "7.40",
        "ValueDay": "0.19",
        "High": "7.45",
        "Low": "7.10",
        "Market": "666.00",
        "TurnOver": "1.86",
        "PE": "-",
        "PBV": "0.71",
        "BookValue": "10.44",
        "Yield": "7.23",
        "cash": "",
        "TotalAsset": "",
        "CurrtLiabilities": ".",
        "TotalLiabilities": "",
        "Equities": "",
        "EBIT": "",
        "EPS": "+",
        "Period": "31/12/2015",
        "AsDate": ""
    },
    {
        "Name": "TIF1",
        "TimeAdd": "2016-08-05T16:23:30.286Z",
        "Quarter": "4",
        "Year": "2015",
        "Date": "Oct-Dec",
        "Closechg": "+0.69",
        "ValueDaychg": "-18.52",
        "Highchg": "-0.66",
        "Lowchg": "-0.69",
        "Marketchg": "+0.69",
        "Turnoverchg": "-17.97",
        "PEchg": "-",
        "PBVchg": "0.00",
        "Yieldchg": "-0.68",
        "BookValuechg": "+0.10",
        "Close": "7.30",
        "ValueDay": "0.16",
        "High": "7.55",
        "Low": "7.15",
        "Market": "657.00",
        "TurnOver": "1.51",
        "PE": "-",
        "PBV": "0.71",
        "BookValue": "10.23",
        "Yield": "7.33",
        "CurrtLiabilities": "",
        "Period": "30/09/2015"
    },
    {
        "Name": "TIF1",
        "TimeAdd": "2016-08-05T16:23:30.286Z",
        "Quarter": "3",
        "Year": "2015",
        "Date": "Jul-Sep",
        "Closechg": "-2.68",
        "ValueDaychg": "-53.10",
        "Highchg": "-1.94",
        "Lowchg": "+1.41",
        "Marketchg": "-2.68",
        "Turnoverchg": "-48.82",
        "PEchg": "-",
        "PBVchg": "-2.74",
        "Yieldchg": "+2.79",
        "BookValuechg": "-0.29",
        "Close": "7.25",
        "ValueDay": "0.20",
        "High": "7.60",
        "Low": "7.20",
        "Market": "652.50",
        "TurnOver": "1.84",
        "PE": "-",
        "PBV": "0.71",
        "BookValue": "10.22",
        "Yield": "7.38",
        "Period": "30/06/2015"
    },
    {
        "Name": "TIF1",
        "TimeAdd": "2016-08-05T16:23:30.286Z",
        "Quarter": "2",
        "Year": "2015",
        "Date": "Apr-Jun",
        "Closechg": "+5.67",
        "ValueDaychg": "-12.08",
        "Highchg": "+5.44",
        "Lowchg": "+2.90",
        "Marketchg": "+5.67",
        "Turnoverchg": "-20.67",
        "PEchg": "-",
        "PBVchg": "+5.80",
        "Yieldchg": "-12.97",
        "BookValuechg": "+0.39",
        "Close": "7.45",
        "ValueDay": "0.42",
        "High": "7.75",
        "Low": "7.10",
        "Market": "670.50",
        "TurnOver": "3.59",
        "PE": "-",
        "PBV": "0.73",
        "BookValue": "10.25",
        "Yield": "7.18",
        "Period": "31/03/2015"
    },
    {
        "Name": "TIF1",
        "TimeAdd": "2016-08-05T16:23:30.286Z",
        "Quarter": "1",
        "Year": "2015",
        "Date": "Jan-Mar",
        "Closechg": "+0.71",
        "ValueDaychg": "-16.51",
        "Highchg": "-8.13",
        "Lowchg": "+1.47",
        "Marketchg": "+0.71",
        "Turnoverchg": "-16.52",
        "PEchg": "-",
        "PBVchg": "0.00",
        "Yieldchg": "-0.60",
        "BookValuechg": "+0.20",
        "Close": "7.05",
        "ValueDay": "0.47",
        "High": "7.35",
        "Low": "6.90",
        "Market": "634.50",
        "TurnOver": "4.53",
        "PE": "-",
        "PBV": "0.69",
        "BookValue": "10.21",
        "Yield": "8.25",
        "Period": "31/12/2014"
    },
    {
        "Name": "TIF1",
        "TimeAdd": "2016-08-05T16:23:30.286Z",
        "Quarter": "4",
        "Year": "2014",
        "Date": "Oct-Dec",
        "Closechg": "-7.28",
        "ValueDaychg": "+54.21",
        "Highchg": "+1.27",
        "Lowchg": "-6.85",
        "Marketchg": "-7.28",
        "Turnoverchg": "+60.78",
        "PEchg": "-",
        "PBVchg": "-6.76",
        "Yieldchg": "+7.79",
        "BookValuechg": "-0.20",
        "Close": "7.00",
        "ValueDay": "0.57",
        "High": "8.00",
        "Low": "6.80",
        "Market": "630.00",
        "TurnOver": "5.42",
        "PE": "-",
        "PBV": "0.69",
        "BookValue": "10.19",
        "Yield": "8.30",
        "Period": "30/09/2014"
    },
    {
        "Name": "TIF1",
        "TimeAdd": "2016-08-05T16:23:30.287Z",
        "Quarter": "3",
        "Year": "2014",
        "Date": "Jul-Sep",
        "Closechg": "+2.72",
        "ValueDaychg": "+21.90",
        "Highchg": "+1.94",
        "Lowchg": "+6.57",
        "Marketchg": "+2.72",
        "Turnoverchg": "+21.71",
        "PEchg": "-",
        "PBVchg": "+2.78",
        "Yieldchg": "-2.65",
        "BookValuechg": "+0.29",
        "Close": "7.55",
        "ValueDay": "0.37",
        "High": "7.90",
        "Low": "7.30",
        "Market": "679.50",
        "TurnOver": "3.37",
        "PE": "-",
        "PBV": "0.74",
        "BookValue": "10.21",
        "Yield": "7.70",
        "Period": "30/06/2014"
    },
    {
        "Name": "TIF1",
        "TimeAdd": "2016-08-05T16:23:30.287Z",
        "Quarter": "2",
        "Year": "2014",
        "Date": "Apr-Jun",
        "Closechg": "+6.52",
        "ValueDaychg": "+60.20",
        "Highchg": "-2.52",
        "Lowchg": "+2.24",
        "Marketchg": "+6.52",
        "Turnoverchg": "+45.96",
        "PEchg": "-",
        "PBVchg": "+5.88",
        "Yieldchg": "+23.98",
        "BookValuechg": "-0.10",
        "Close": "7.35",
        "ValueDay": "0.30",
        "High": "7.75",
        "Low": "6.85",
        "Market": "661.50",
        "TurnOver": "2.77",
        "PE": "-",
        "PBV": "0.72",
        "BookValue": "10.18",
        "Yield": "7.91",
        "Period": "31/03/2014"
    },
    {
        "Name": "TIF1",
        "TimeAdd": "2016-08-05T16:23:30.287Z",
        "Quarter": "1",
        "Year": "2014",
        "Date": "Jan-Mar",
        "Closechg": "+0.73",
        "ValueDaychg": "+45.27",
        "Highchg": "-0.62",
        "Lowchg": "0.00",
        "Marketchg": "+0.73",
        "Turnoverchg": "+45.96",
        "PEchg": "-",
        "PBVchg": "+1.49",
        "Yieldchg": "-0.62",
        "BookValuechg": "+0.39",
        "Close": "6.90",
        "ValueDay": "0.19",
        "High": "7.95",
        "Low": "6.70",
        "Market": "621.00",
        "TurnOver": "1.90",
        "PE": "-",
        "PBV": "0.68",
        "BookValue": "10.19",
        "Yield": "6.38",
        "Period": "31/12/2013"
    },
    {
        "Name": "TIF1",
        "TimeAdd": "2016-08-05T16:23:30.287Z",
        "Quarter": "4",
        "Year": "2013",
        "Date": "Oct-Dec",
        "Closechg": "+0.74",
        "ValueDaychg": "+33.24",
        "Highchg": "0.00",
        "Lowchg": "+0.75",
        "Marketchg": "+0.74",
        "Turnoverchg": "+30.47",
        "PEchg": "-",
        "PBVchg": "0.00",
        "Yieldchg": "-0.77",
        "BookValuechg": "+0.59",
        "Close": "6.85",
        "ValueDay": "0.13",
        "High": "8.00",
        "Low": "6.70",
        "Market": "616.50",
        "TurnOver": "1.30",
        "PE": "-",
        "PBV": "0.67",
        "BookValue": "10.15",
        "Yield": "6.42",
        "Period": "30/09/2013"
    },
    {
        "Name": "TIF1",
        "TimeAdd": "2016-08-05T16:23:30.287Z",
        "Quarter": "3",
        "Year": "2013",
        "Date": "Jul-Sep",
        "Closechg": "0.00",
        "ValueDaychg": "-64.85",
        "Highchg": "+0.63",
        "Lowchg": "-0.75",
        "Marketchg": "0.00",
        "Turnoverchg": "-60.64",
        "PEchg": "-",
        "PBVchg": "-1.47",
        "Yieldchg": "0.00",
        "BookValuechg": "+0.30",
        "Close": "6.80",
        "ValueDay": "0.10",
        "High": "8.00",
        "Low": "6.65",
        "Market": "612.00",
        "TurnOver": "1.00",
        "PE": "-",
        "PBV": "0.67",
        "BookValue": "10.09",
        "Yield": "6.47",
        "Period": "30/06/2013"
    },
    {
        "Name": "TIF1",
        "TimeAdd": "2016-08-05T16:23:30.287Z",
        "Quarter": "2",
        "Year": "2013",
        "Date": "Apr-Jun",
        "Closechg": "-8.11",
        "ValueDaychg": "+23.20",
        "Highchg": "+3.25",
        "Lowchg": "0.00",
        "Marketchg": "-8.11",
        "Turnoverchg": "+22.99",
        "PEchg": "-",
        "PBVchg": "-8.11",
        "Yieldchg": "-3.29",
        "BookValuechg": "+0.10",
        "Close": "6.80",
        "ValueDay": "0.28",
        "High": "7.95",
        "Low": "6.70",
        "Market": "612.00",
        "TurnOver": "2.53",
        "PE": "-",
        "PBV": "0.68",
        "BookValue": "10.06",
        "Yield": "6.47",
        "Period": "31/03/2013"
    },
    {
        "Name": "TIF1",
        "TimeAdd": "2016-08-05T16:23:30.287Z",
        "Quarter": "1",
        "Year": "2013",
        "Date": "Jan-Mar",
        "Closechg": "-2.63",
        "ValueDaychg": "+127.41",
        "Highchg": "-1.28",
        "Lowchg": "+3.08",
        "Marketchg": "-2.63",
        "Turnoverchg": "+130.05",
        "PEchg": "-",
        "PBVchg": "-3.90",
        "Yieldchg": "+2.76",
        "BookValuechg": "+2.03",
        "Close": "7.40",
        "ValueDay": "0.22",
        "High": "7.70",
        "Low": "6.70",
        "Market": "666.00",
        "TurnOver": "2.06",
        "PE": "-",
        "PBV": "0.74",
        "BookValue": "10.05",
        "Yield": "6.69",
        "Period": "31/12/2012"
    },
    {
        "Name": "TIF1",
        "TimeAdd": "2016-08-05T16:23:30.288Z",
        "Quarter": "4",
        "Year": "2012",
        "Date": "Oct-Dec",
        "Closechg": "-0.65",
        "ValueDaychg": "-2.33",
        "Highchg": "-2.50",
        "Lowchg": "-13.33",
        "Marketchg": "-0.65",
        "Turnoverchg": "-3.44",
        "PEchg": "-",
        "PBVchg": "-1.28",
        "Yieldchg": "+0.62",
        "BookValuechg": "-1.30",
        "Close": "7.60",
        "ValueDay": "0.10",
        "High": "7.80",
        "Low": "6.50",
        "Market": "684.00",
        "TurnOver": "0.90",
        "PE": "-",
        "PBV": "0.77",
        "BookValue": "9.85",
        "Yield": "6.51",
        "Period": "30/09/2012"
    },
    {
        "Name": "TIF1",
        "TimeAdd": "2016-08-05T16:23:30.288Z",
        "Quarter": "3",
        "Year": "2012",
        "Date": "Jul-Sep",
        "Closechg": "+0.66",
        "ValueDaychg": "+26.18",
        "Highchg": "0.00",
        "Lowchg": "+6.38",
        "Marketchg": "+0.66",
        "Turnoverchg": "+39.09",
        "PEchg": "-",
        "PBVchg": "+2.63",
        "Yieldchg": "-0.61",
        "BookValuechg": "-2.16",
        "Close": "7.65",
        "ValueDay": "0.10",
        "High": "8.00",
        "Low": "7.50",
        "Market": "688.50",
        "TurnOver": "0.93",
        "PE": "-",
        "PBV": "0.78",
        "BookValue": "9.98",
        "Yield": "6.47",
        "Period": "30/06/2012"
    },
    {
        "Name": "TIF1",
        "TimeAdd": "2016-08-05T16:23:30.288Z",
        "Quarter": "2",
        "Year": "2012",
        "Date": "Apr-Jun",
        "Closechg": "-3.18",
        "ValueDaychg": "+83.80",
        "Highchg": "-2.44",
        "Lowchg": "-7.24",
        "Marketchg": "-3.18",
        "Turnoverchg": "+74.07",
        "PEchg": "-",
        "PBVchg": "-5.00",
        "Yieldchg": "+9.60",
        "BookValuechg": "+1.80",
        "Close": "7.60",
        "ValueDay": "0.08",
        "High": "8.00",
        "Low": "7.05",
        "Market": "684.00",
        "TurnOver": "0.67",
        "PE": "-",
        "PBV": "0.76",
        "BookValue": "10.20",
        "Yield": "6.51",
        "Period": "31/03/2012"
    },
    {
        "Name": "TIF1",
        "TimeAdd": "2016-08-05T16:23:30.288Z",
        "Quarter": "1",
        "Year": "2012",
        "Date": "Jan-Mar",
        "Closechg": "-1.88",
        "ValueDaychg": "+14.28",
        "Highchg": "+2.50",
        "Lowchg": "+16.03",
        "Marketchg": "-1.88",
        "Turnoverchg": "+12.64",
        "PEchg": "-",
        "PBVchg": "0.00",
        "Yieldchg": "+1.89",
        "BookValuechg": "-1.67",
        "Close": "7.85",
        "ValueDay": "0.04",
        "High": "8.20",
        "Low": "7.60",
        "Market": "706.50",
        "TurnOver": "0.38",
        "PE": "-",
        "PBV": "0.80",
        "BookValue": "10.02",
        "Yield": "5.94",
        "Period": "31/12/2011"
    },
    {
        "Name": "TIF1",
        "TimeAdd": "2016-08-05T16:23:30.288Z",
        "Quarter": "4",
        "Year": "2011",
        "Date": "Oct-Dec",
        "Closechg": "-1.23",
        "ValueDaychg": "-58.84",
        "Highchg": "-5.33",
        "Lowchg": "-17.09",
        "Marketchg": "-1.23",
        "Turnoverchg": "-57.33",
        "PEchg": "-",
        "PBVchg": "-1.23",
        "Yieldchg": "+1.39",
        "BookValuechg": "-0.20",
        "Close": "8.00",
        "ValueDay": "0.04",
        "High": "8.00",
        "Low": "6.55",
        "Market": "720.00",
        "TurnOver": "0.34",
        "PE": "-",
        "PBV": "0.80",
        "BookValue": "10.19",
        "Yield": "5.83",
        "Period": "30/09/2011"
    },
    {
        "Name": "TIF1",
        "TimeAdd": "2016-08-05T16:23:30.289Z",
        "Quarter": "3",
        "Year": "2011",
        "Date": "Jul-Sep",
        "Closechg": "-0.61",
        "ValueDaychg": "+66.90",
        "Highchg": "+1.81",
        "Lowchg": "0.00",
        "Marketchg": "-0.61",
        "Turnoverchg": "+84.92",
        "PEchg": "-",
        "PBVchg": "+1.25",
        "Yieldchg": "+0.52",
        "BookValuechg": "+0.49",
        "Close": "8.10",
        "ValueDay": "0.09",
        "High": "8.45",
        "Low": "7.90",
        "Market": "729.00",
        "TurnOver": "0.80",
        "PE": "-",
        "PBV": "0.81",
        "BookValue": "10.21",
        "Yield": "5.75",
        "Period": "30/06/2011"
    },
    {
        "Name": "TIF1",
        "TimeAdd": "2016-08-05T16:23:30.289Z",
        "Quarter": "2",
        "Year": "2011",
        "Date": "Apr-Jun",
        "Closechg": "0.00",
        "ValueDaychg": "-54.65",
        "Highchg": "-4.60",
        "Lowchg": "-1.86",
        "Marketchg": "0.00",
        "Turnoverchg": "-58.10",
        "PEchg": "-",
        "PBVchg": "-1.23",
        "Yieldchg": "-16.74",
        "BookValuechg": "+1.50",
        "Close": "8.15",
        "ValueDay": "0.06",
        "High": "8.30",
        "Low": "7.90",
        "Market": "733.50",
        "TurnOver": "0.43",
        "PE": "-",
        "PBV": "0.80",
        "BookValue": "10.16",
        "Yield": "5.72",
        "Period": "31/03/2011"
    },
    {
        "Name": "TIF1",
        "TimeAdd": "2016-08-05T16:23:30.289Z",
        "Quarter": "1",
        "Year": "2011",
        "Date": "Jan-Mar",
        "Closechg": "+1.24",
        "ValueDaychg": "-64.64",
        "Highchg": "+6.75",
        "Lowchg": "+0.63",
        "Marketchg": "+1.24",
        "Turnoverchg": "-65.18",
        "PEchg": "-18.16",
        "PBVchg": "+2.53",
        "Yieldchg": "-1.29",
        "BookValuechg": "-2.05",
        "Close": "8.15",
        "ValueDay": "0.12",
        "High": "8.70",
        "Low": "8.05",
        "Market": "733.50",
        "TurnOver": "1.03",
        "PE": "8.11",
        "PBV": "0.81",
        "BookValue": "10.01",
        "Yield": "6.87",
        "Period": "31/12/2010"
    },
    {
        "Name": "TIF1",
        "TimeAdd": "2016-08-05T16:23:30.289Z",
        "Quarter": "4",
        "Year": "2010",
        "Date": "Oct-Dec",
        "Closechg": "-0.62",
        "ValueDaychg": "+231.62",
        "Highchg": "-5.78",
        "Lowchg": "+39.13",
        "Marketchg": "-0.62",
        "Turnoverchg": "+230.11",
        "PEchg": "-4.16",
        "PBVchg": "0.00",
        "Yieldchg": "+0.72",
        "BookValuechg": "+0.20",
        "Close": "8.05",
        "ValueDay": "0.35",
        "High": "8.15",
        "Low": "8.00",
        "Market": "724.50",
        "TurnOver": "2.95",
        "PE": "9.91",
        "PBV": "0.79",
        "BookValue": "10.22",
        "Yield": "6.96",
        "Period": "30/09/2010"
    },
    {
        "Name": "TIF1",
        "TimeAdd": "2016-08-05T16:23:30.289Z",
        "Quarter": "3",
        "Year": "2010",
        "Date": "Jul-Sep",
        "Closechg": "-1.82",
        "ValueDaychg": "+226.46",
        "Highchg": "+1.76",
        "Lowchg": "-21.23",
        "Marketchg": "-1.82",
        "Turnoverchg": "+238.40",
        "PEchg": "-31.70",
        "PBVchg": "-2.47",
        "Yieldchg": "+1.77",
        "BookValuechg": "0.00",
        "Close": "8.10",
        "ValueDay": "0.10",
        "High": "8.65",
        "Low": "5.75",
        "Market": "729.00",
        "TurnOver": "0.89",
        "PE": "10.34",
        "PBV": "0.79",
        "BookValue": "10.20",
        "Yield": "6.91",
        "Period": "30/06/2010"
    },
    {
        "Name": "TIF1",
        "TimeAdd": "2016-08-05T16:23:30.290Z",
        "Quarter": "2",
        "Year": "2010",
        "Date": "Apr-Jun",
        "Closechg": "+11.49",
        "ValueDaychg": "-83.36",
        "Highchg": "+11.84",
        "Lowchg": "+4.29",
        "Marketchg": "+11.49",
        "Turnoverchg": "-85.56",
        "PEchg": "-9.23",
        "PBVchg": "+10.96",
        "Yieldchg": "-22.13",
        "BookValuechg": "+0.29",
        "Close": "8.25",
        "ValueDay": "0.03",
        "High": "8.50",
        "Low": "7.30",
        "Market": "742.50",
        "TurnOver": "0.26",
        "PE": "15.14",
        "PBV": "0.81",
        "BookValue": "10.20",
        "Yield": "6.79",
        "Period": "31/03/2010"
    },
    {
        "Name": "TIF1",
        "TimeAdd": "2016-08-05T16:23:30.290Z",
        "Quarter": "1",
        "Year": "2010",
        "Date": "Jan-Mar",
        "Closechg": "-1.99",
        "ValueDaychg": "+154.88",
        "Highchg": "-5.00",
        "Lowchg": "+0.72",
        "Marketchg": "-1.99",
        "Turnoverchg": "+154.31",
        "PEchg": "-13.40",
        "PBVchg": "-1.35",
        "Yieldchg": "+2.11",
        "BookValuechg": "+0.20",
        "Close": "7.40",
        "ValueDay": "0.19",
        "High": "7.60",
        "Low": "7.00",
        "Market": "666.00",
        "TurnOver": "1.83",
        "PE": "16.68",
        "PBV": "0.73",
        "BookValue": "10.17",
        "Yield": "8.72",
        "Period": "31/12/2009"
    },
    {
        "Name": "TIF1",
        "TimeAdd": "2016-08-05T16:23:30.291Z",
        "Quarter": "4",
        "Year": "2009",
        "Date": "Oct-Dec",
        "Closechg": "+8.63",
        "ValueDaychg": "-76.31",
        "Highchg": "+13.48",
        "Lowchg": "+2.96",
        "Marketchg": "+8.63",
        "Turnoverchg": "-77.49",
        "PEchg": "-5.63",
        "PBVchg": "+8.82",
        "Yieldchg": "-7.97",
        "BookValuechg": "-0.10",
        "Close": "7.55",
        "ValueDay": "0.08",
        "High": "8.00",
        "Low": "6.95",
        "Market": "679.50",
        "TurnOver": "0.72",
        "PE": "19.26",
        "PBV": "0.74",
        "BookValue": "10.15",
        "Yield": "8.54",
        "Period": "30/09/2009"
    },
    {
        "Name": "TIF1",
        "TimeAdd": "2016-08-05T16:23:30.291Z",
        "Quarter": "3",
        "Year": "2009",
        "Date": "Jul-Sep",
        "Closechg": "+0.72",
        "ValueDaychg": "+24.22",
        "Highchg": "-24.60",
        "Lowchg": "-0.74",
        "Marketchg": "+0.72",
        "Turnoverchg": "+37.73",
        "PEchg": "+234.04",
        "PBVchg": "0.00",
        "Yieldchg": "-0.75",
        "BookValuechg": "-0.10",
        "Close": "6.95",
        "ValueDay": "0.32",
        "High": "7.05",
        "Low": "6.75",
        "Market": "625.50",
        "TurnOver": "3.20",
        "PE": "20.41",
        "PBV": "0.68",
        "BookValue": "10.16",
        "Yield": "9.28",
        "Period": "30/06/2009"
    },
    {
        "Name": "TIF1",
        "TimeAdd": "2016-08-05T16:23:30.291Z",
        "Quarter": "2",
        "Year": "2009",
        "Date": "Apr-Jun",
        "Closechg": "+0.73",
        "ValueDaychg": "+605.77",
        "Highchg": "+16.87",
        "Lowchg": "-0.73",
        "Marketchg": "+0.73",
        "Turnoverchg": "+599.13",
        "PEchg": "+0.16",
        "PBVchg": "+7.94",
        "Yieldchg": "-13.02",
        "BookValuechg": "-5.83",
        "Close": "6.90",
        "ValueDay": "0.26",
        "High": "9.35",
        "Low": "6.80",
        "Market": "621.00",
        "TurnOver": "2.32",
        "PE": "6.11",
        "PBV": "0.68",
        "BookValue": "10.17",
        "Yield": "9.35",
        "Period": "31/03/2009"
    },
    {
        "Name": "TIF1",
        "TimeAdd": "2016-08-05T16:23:30.291Z",
        "Quarter": "1",
        "Year": "2009",
        "Date": "Jan-Mar",
        "Closechg": "-7.43",
        "ValueDaychg": "-54.23",
        "Highchg": "-16.67",
        "Lowchg": "-2.84",
        "Marketchg": "-7.43",
        "Turnoverchg": "-50.49",
        "PEchg": "+1.67",
        "PBVchg": "-",
        "Yieldchg": "+8.04",
        "BookValuechg": "-",
        "Close": "6.85",
        "ValueDay": "0.04",
        "High": "8.00",
        "Low": "6.85",
        "Market": "616.50",
        "TurnOver": "0.33",
        "PE": "6.10",
        "PBV": "0.63",
        "BookValue": "10.80",
        "Yield": "10.75",
        "Period": "31/12/2008"
    },
    {
        "Name": "TIF1",
        "TimeAdd": "2016-08-05T16:23:30.291Z",
        "Quarter": "4",
        "Year": "2008",
        "Date": "Oct-Dec",
        "Closechg": "-21.28",
        "ValueDaychg": "+22.22",
        "Highchg": "-2.04",
        "Lowchg": "-25.00",
        "Marketchg": "-21.28",
        "Turnoverchg": "+42.44",
        "PEchg": "-13.67",
        "PBVchg": "-",
        "Yieldchg": "+27.08",
        "BookValuechg": "-",
        "Close": "7.40",
        "ValueDay": "0.08",
        "High": "9.60",
        "Low": "7.05",
        "Market": "666.00",
        "TurnOver": "0.67",
        "PE": "6.00",
        "PBV": "-",
        "BookValue": "-",
        "Yield": "9.95",
        "Period": "30/09/2008"
    },
    {
        "Name": "TIF1",
        "TimeAdd": "2016-08-05T16:23:30.293Z",
        "Quarter": "3",
        "Year": "2008",
        "Date": "Jul-Sep",
        "Closechg": "-4.08",
        "ValueDaychg": "-90.68",
        "Highchg": "-2.00",
        "Lowchg": "-3.09",
        "Marketchg": "-4.08",
        "Turnoverchg": "-89.82",
        "PEchg": "-",
        "PBVchg": "-",
        "Yieldchg": "+4.26",
        "BookValuechg": "-",
        "Close": "9.40",
        "ValueDay": "0.06",
        "High": "9.80",
        "Low": "9.40",
        "Market": "846.00",
        "TurnOver": "0.47",
        "PE": "6.95",
        "PBV": "-",
        "BookValue": "-",
        "Yield": "7.83",
        "Period": "31/03/2008"
    },
    {
        "Name": "TIF1",
        "TimeAdd": "2016-08-05T16:23:30.293Z",
        "Quarter": "2",
        "Year": "2008",
        "Date": "Apr-Jun",
        "Closechg": "-1.01",
        "ValueDaychg": "+1.28",
        "Highchg": "-0.99",
        "Lowchg": "-1.52",
        "Marketchg": "-1.01",
        "Turnoverchg": "-4.09",
        "PEchg": "-",
        "PBVchg": "-",
        "Yieldchg": "+55.81",
        "BookValuechg": "-",
        "Close": "9.80",
        "ValueDay": "0.70",
        "High": "10.00",
        "Low": "9.70",
        "Market": "882.00",
        "TurnOver": "4.63",
        "PE": "-",
        "PBV": "-",
        "BookValue": "-",
        "Yield": "7.51",
        "Period": "31/03/2008"
    },
    {
        "Name": "TIF1",
        "TimeAdd": "2016-08-05T16:23:30.293Z",
        "Quarter": "1",
        "Year": "2008",
        "Date": "Jan-Mar",
        "Closechg": "-1.00",
        "ValueDaychg": "+40.01",
        "Highchg": "-0.98",
        "Lowchg": "-1.01",
        "Marketchg": "-1.00",
        "Turnoverchg": "+45.47",
        "PEchg": "-",
        "PBVchg": "-",
        "Yieldchg": "+1.05",
        "BookValuechg": "-",
        "Close": "9.90",
        "ValueDay": "0.69",
        "High": "10.10",
        "Low": "9.85",
        "Market": "891.00",
        "TurnOver": "4.83",
        "PE": "-",
        "PBV": "-",
        "BookValue": "-",
        "Yield": "4.82",
        "Period": "31/12/2007"
    },
    {
        "Name": "TIF1",
        "TimeAdd": "2016-08-05T16:23:30.293Z",
        "Quarter": "4",
        "Year": "2007",
        "Date": "Oct-Dec",
        "Closechg": "-0.99",
        "ValueDaychg": "+44.11",
        "Highchg": "-0.97",
        "Lowchg": "-1.49",
        "Marketchg": "-0.99",
        "Turnoverchg": "+41.69",
        "PEchg": "-",
        "PBVchg": "-",
        "Yieldchg": "+1.06",
        "BookValuechg": "-",
        "Close": "10.00",
        "ValueDay": "0.49",
        "High": "10.20",
        "Low": "9.95",
        "Market": "900.00",
        "TurnOver": "3.32",
        "PE": "-",
        "PBV": "-",
        "BookValue": "-",
        "Yield": "4.77",
        "Period": "30/09/2007"
    },
    {
        "Name": "TIF1",
        "TimeAdd": "2016-08-05T16:23:30.294Z",
        "Quarter": "3",
        "Year": "2007",
        "Date": "Jul-Sep",
        "Closechg": "-0.98",
        "ValueDaychg": "+34.66",
        "Highchg": "-0.96",
        "Lowchg": "+2.02",
        "Marketchg": "-0.98",
        "Turnoverchg": "-5.87",
        "PBVchg": "-",
        "Yieldchg": "+0.85",
        "BookValuechg": "-",
        "Close": "10.10",
        "ValueDay": "0.34",
        "High": "10.30",
        "Low": "10.10",
        "Market": "909.00",
        "TurnOver": "2.34",
        "PE": "",
        "PBV": "-",
        "BookValue": "-",
        "Yield": "4.72",
        "Period": "30/06/2007"
    },
    {
        "Name": "TIF1",
        "TimeAdd": "2016-08-05T16:23:30.294Z",
        "Quarter": "2",
        "Year": "2007",
        "Date": "Apr-Jun",
        "Closechg": "+2.00",
        "ValueDaychg": "+871.64",
        "Highchg": "+2.97",
        "Lowchg": "+5.32",
        "Marketchg": "+81.78",
        "Turnoverchg": "+673.20",
        "PBVchg": "-",
        "Yieldchg": "-28.55",
        "BookValuechg": "-",
        "Close": "10.20",
        "ValueDay": "0.25",
        "High": "10.40",
        "Low": "9.90",
        "Market": "918.00",
        "TurnOver": "2.49",
        "PBV": "-",
        "BookValue": "-",
        "Yield": "4.68",
        "Period": "31/03/2007"
    },
    {
        "Name": "TIF1",
        "TimeAdd": "2016-08-05T16:23:30.294Z",
        "Quarter": "1",
        "Year": "2007",
        "Date": "Jan-Mar",
        "Closechg": "+1.52",
        "ValueDaychg": "+12.93",
        "Highchg": "+1.00",
        "Lowchg": "-3.09",
        "Marketchg": "+1.52",
        "Turnoverchg": "+11.91",
        "PBVchg": "-",
        "Yieldchg": "-1.50",
        "BookValuechg": "-",
        "Close": "10.00",
        "ValueDay": "0.03",
        "High": "10.10",
        "Low": "9.40",
        "Market": "505.00",
        "TurnOver": "0.32",
        "PBV": "-",
        "BookValue": "-",
        "Yield": "6.55",
        "Period": "31/12/2006"
    },
    {
        "Name": "TIF1",
        "TimeAdd": "2016-08-05T16:23:30.294Z",
        "Quarter": "4",
        "Year": "2006",
        "Date": "Oct-Dec",
        "Closechg": "+3.14",
        "ValueDaychg": "-77.98",
        "Highchg": "+1.01",
        "Lowchg": "+2.11",
        "Marketchg": "+3.14",
        "Turnoverchg": "-78.48",
        "PBVchg": "-",
        "Yieldchg": "-3.06",
        "BookValuechg": "-",
        "Close": "9.85",
        "ValueDay": "0.02",
        "High": "10.00",
        "Low": "9.70",
        "Market": "497.43",
        "TurnOver": "0.29",
        "PBV": "-",
        "BookValue": "-",
        "Yield": "6.65",
        "Period": "30/09/2006"
    },
    {
        "Name": "TIF1",
        "TimeAdd": "2016-08-05T16:23:30.294Z",
        "Quarter": "3",
        "Year": "2006",
        "Date": "Jul-Sep",
        "Closechg": "-2.05",
        "ValueDaychg": "-25.71",
        "Highchg": "-2.94",
        "Lowchg": "-2.56",
        "Marketchg": "-2.05",
        "Turnoverchg": "-14.70",
        "PBVchg": "-",
        "Yieldchg": "+2.08",
        "BookValuechg": "-",
        "Close": "9.55",
        "ValueDay": "0.10",
        "High": "9.90",
        "Low": "9.50",
        "Market": "482.28",
        "TurnOver": "1.34",
        "PBV": "-",
        "BookValue": "-",
        "Yield": "6.86",
        "Period": "30/06/2006"
    },
    {
        "Name": "TIF1",
        "TimeAdd": "2016-08-05T16:23:30.295Z",
        "Quarter": "2",
        "Year": "2006",
        "Date": "Apr-Jun",
        "Closechg": "-2.50",
        "ValueDaychg": "+13.75",
        "Highchg": "-3.77",
        "Lowchg": "-1.52",
        "Marketchg": "-2.50",
        "Turnoverchg": "+1.59",
        "PBVchg": "-",
        "Yieldchg": "-",
        "BookValuechg": "-",
        "Close": "9.75",
        "ValueDay": "0.14",
        "High": "10.20",
        "Low": "9.75",
        "Market": "492.38",
        "TurnOver": "1.57",
        "PBV": "-",
        "BookValue": "-",
        "Yield": "6.72",
        "Period": "31/03/2006"
    },
    {
        "Name": "TIF1",
        "TimeAdd": "2016-08-05T16:23:30.295Z",
        "Quarter": "1",
        "Year": "2006",
        "Date": "Jan-Mar",
        "Closechg": "+0.50",
        "ValueDaychg": "+391.80",
        "Highchg": "+4.95",
        "Lowchg": "+0.51",
        "Marketchg": "+0.50",
        "Turnoverchg": "+396.18",
        "PBVchg": "-",
        "Yieldchg": "-",
        "BookValuechg": "-",
        "Close": "10.00",
        "ValueDay": "0.12",
        "High": "10.60",
        "Low": "9.90",
        "Market": "505.00",
        "TurnOver": "1.54",
        "PBV": "-",
        "BookValue": "-",
        "Yield": "-",
        "Period": "31/12/2005"
    },
    {
        "Name": "TIF1",
        "TimeAdd": "2016-08-05T16:23:30.295Z",
        "Quarter": "4",
        "Year": "2005",
        "Date": "Oct-Dec",
        "Closechg": "-1.49",
        "ValueDaychg": "+195.11",
        "Highchg": "-0.98",
        "Lowchg": "-1.50",
        "Marketchg": "-1.49",
        "Turnoverchg": "+192.72",
        "PBVchg": "-",
        "Yieldchg": "-",
        "BookValuechg": "-",
        "Close": "9.95",
        "ValueDay": "0.03",
        "High": "10.10",
        "Low": "9.85",
        "Market": "502.48",
        "TurnOver": "0.31",
        "PBV": "-",
        "BookValue": "-",
        "Yield": "-",
        "Period": "30/09/2005"
    },
    {
        "Name": "TIF1",
        "TimeAdd": "2016-08-05T16:23:30.295Z",
        "Quarter": "3",
        "Year": "2005",
        "Date": "Jul-Sep",
        "Closechg": "+1.00",
        "ValueDaychg": "-98.71",
        "Highchg": "0.00",
        "Lowchg": "+0.50",
        "Marketchg": "+1.00",
        "Turnoverchg": "-59.15",
        "PBVchg": "-",
        "Yieldchg": "-",
        "BookValuechg": "-",
        "Close": "10.10",
        "ValueDay": "0.01",
        "High": "10.20",
        "Low": "10.00",
        "Market": "510.05",
        "TurnOver": "0.11",
        "PBV": "-",
        "BookValue": "-",
        "Yield": "-",
        "Period": "30/06/2005"
    }
]